odoo/addons/cooperator_documentation/README.rst
odoo/addons/cooperator_documentation/__init__.py
odoo/addons/cooperator_documentation/__manifest__.py
odoo/addons/cooperator_documentation/i18n/cooperator_documentation.pot
odoo/addons/cooperator_documentation/i18n/it.po
odoo/addons/cooperator_documentation/i18n/pt_BR.po
odoo/addons/cooperator_documentation/readme/CONTRIBUTORS.rst
odoo/addons/cooperator_documentation/readme/DESCRIPTION.rst
odoo/addons/cooperator_documentation/static/description/icon.png
odoo/addons/cooperator_documentation/static/description/index.html
odoo/addons/cooperator_documentation/views/menus.xml
odoo_addon_cooperator_documentation-16.0.1.0.0.6.dist-info/METADATA
odoo_addon_cooperator_documentation-16.0.1.0.0.6.dist-info/WHEEL
odoo_addon_cooperator_documentation-16.0.1.0.0.6.dist-info/top_level.txt
odoo_addon_cooperator_documentation-16.0.1.0.0.6.dist-info/RECORD
